<?xml version="1.0" encoding="UTF-8" standalone="yes"?>
<root>
<!-- 第一版单位：法术部分 -->
	<item id="23100"/>
	<item id="23101"/>
	<item id="23102"/>
	<item id="23103"/>
	<item id="23104"/>
	<item id="23105"/>
	<item id="23106"/>
	<item id="23107"/>
	<item id="23108"/>
	<item id="23109"/>    
<!-- 第一版单位：单位部分 -->	
	<item id="22000"/>
	<item id="22001"/>
	<item id="22002"/>
	<item id="22003"/>
	<item id="22004"/>
	<item id="22005"/>
	<item id="22006"/>
	<item id="22007"/>
	<item id="22008"/>
	<item id="22009"/>
	<item id="22010"/>
	<item id="22011"/>
	
	<item id="22012"/>
	<item id="22013"/>
	
	<item id="22014"/>
	<item id="22015"/>
	<item id="22016"/>
	<item id="22017"/>
	<item id="22018"/>
<!-- 第一版单位：英雄部分 -->		
	<item id="21100"/>
	<item id="21101"/>
	<item id="21102"/>
	<item id="21103"/>
	<item id="21104"/>
	<item id="21105"/>
	<item id="21106"/>
	<item id="21107"/>
	<item id="21108"/>
	<item id="21109"/>
	
	<item id="21110"/>
	<item id="21111"/>
</root>